gjaischool_submit/keyword.py
gjaischool_submit-0.0.0.1.dist-info/METADATA
gjaischool_submit-0.0.0.1.dist-info/WHEEL
gjaischool_submit-0.0.0.1.dist-info/top_level.txt
gjaischool_submit-0.0.0.1.dist-info/RECORD
