Metadata-Version: 2.1
Name: gjaischool-submit
Version: 0.0.0.1
Summary: 광주ai사관학교 4기 제출용
Home-page: UNKNOWN
Author: mmopg42
Author-email: mmopg42@gmail.com
License: MIT
Platform: UNKNOWN
Requires-Python: >=3
